grokmirror/__init__.py
grokmirror/bundle.py
grokmirror/dumb_pull.py
grokmirror/fsck.py
grokmirror/manifest.py
grokmirror/pi_piper.py
grokmirror/pull.py
grokmirror-2.0.12.dist-info/LICENSE.txt
grokmirror-2.0.12.dist-info/METADATA
grokmirror-2.0.12.dist-info/WHEEL
grokmirror-2.0.12.dist-info/entry_points.txt
grokmirror-2.0.12.dist-info/top_level.txt
grokmirror-2.0.12.dist-info/RECORD
