Metadata-Version: 2.1
Name: grokmirror
Version: 2.0.12
Summary: Smartly mirror git repositories that use grokmirror
Home-page: https://git.kernel.org/pub/scm/utils/grokmirror/grokmirror.git
Download-URL: https://www.kernel.org/pub/software/network/grokmirror/grokmirror-2.0.12.tar.xz
Author: Konstantin Ryabitsev
Author-email: konstantin@linuxfoundation.org
License: GPLv3+
Project-URL: Source, https://git.kernel.org/pub/scm/utils/grokmirror/grokmirror.git
Project-URL: Tracker, https://github.com/mricon/grokmirror/issues
Keywords: git,mirroring,repositories
Requires-Python: >=3.6
License-File: LICENSE.txt
Requires-Dist: requests
